perplexica_mcp/__init__.py
perplexica_mcp/__main__.py
perplexica_mcp/server.py
perplexica_mcp-0.3.4.dist-info/METADATA
perplexica_mcp-0.3.4.dist-info/WHEEL
perplexica_mcp-0.3.4.dist-info/entry_points.txt
perplexica_mcp-0.3.4.dist-info/licenses/LICENSE
perplexica_mcp-0.3.4.dist-info/RECORD
