Metadata-Version: 2.4
Name: perplexica-mcp
Version: 0.3.4
Summary: A Model Context Protocol (MCP) server that provides search functionality using Perplexica's AI-powered search engine
Project-URL: Homepage, https://github.com/thetom42/perplexica-mcp
Project-URL: Repository, https://github.com/thetom42/perplexica-mcp
Project-URL: Issues, https://github.com/thetom42/perplexica-mcp/issues
Project-URL: Documentation, https://github.com/thetom42/perplexica-mcp#readme
Author-email: thetom42 <thetom42@gmail.com>
Maintainer-email: thetom42 <thetom42@gmail.com>
License-Expression: MIT
License-File: LICENSE
Keywords: ai,llm,mcp,model-context-protocol,perplexica,search
Classifier: Development Status :: 4 - Beta
Classifier: Intended Audience :: Developers
Classifier: License :: OSI Approved :: MIT License
Classifier: Operating System :: OS Independent
Classifier: Programming Language :: Python :: 3
Classifier: Programming Language :: Python :: 3.12
Classifier: Programming Language :: Python :: 3.13
Classifier: Topic :: Internet :: WWW/HTTP :: Indexing/Search
Classifier: Topic :: Scientific/Engineering :: Artificial Intelligence
Classifier: Topic :: Software Development :: Libraries :: Python Modules
Requires-Python: >=3.12
Requires-Dist: httpx
Requires-Dist: mcp[cli]
Requires-Dist: python-dotenv
Requires-Dist: uvicorn
Provides-Extra: dev
Requires-Dist: black; extra == 'dev'
Requires-Dist: isort; extra == 'dev'
Requires-Dist: mypy; extra == 'dev'
Requires-Dist: pytest; extra == 'dev'
Requires-Dist: pytest-asyncio; extra == 'dev'
